{
  "kind": "collectionType",
  "collectionName": "projects",
  "info": {
    "singularName": "project",
    "pluralName": "projects",
    "displayName": "Project",
    "description": "Portfolio projects displayed in the Projects tab"
  },
  "options": {
    "draftAndPublish": true
  },
  "attributes": {
    "title": {
      "type": "string",
      "required": false
    },
    "description": {
      "type": "text"
    },
    "image": {
      "type": "media",
      "multiple": false,
      "required": false,
      "allowedTypes": ["images"]
    },
    "language": {
      "type": "string",
      "required": true
    },
    "author": {
      "type": "string",
      "required": true
    },
    "grade": {
      "type": "string",
      "required": true
    },
    "isSaved": {
      "type": "boolean",
      "default": false
    },
    "isShared": {
      "type": "boolean",
      "default": false
    },
    "isAchievement": {
      "type": "boolean",
      "default": false
    }
  }
}
